spec_plots/__init__.py
spec_plots/__main__.py
spec_plots/__main_jwst__.py
spec_plots/make_hst_spec_previews.py
spec_plots/make_html.py
spec_plots/make_jwst_spec_previews.py
spec_plots/utils/__init__.py
spec_plots/utils/specutils/__init__.py
spec_plots/utils/specutils/avoidregion.py
spec_plots/utils/specutils/calc_covering_fraction.py
spec_plots/utils/specutils/calc_plot_metrics.py
spec_plots/utils/specutils/debug_oplot.py
spec_plots/utils/specutils/dq_has_flag.py
spec_plots/utils/specutils/edge_trim.py
spec_plots/utils/specutils/get_flux_stats.py
spec_plots/utils/specutils/is_bad_dq.py
spec_plots/utils/specutils/rms.py
spec_plots/utils/specutils/set_plot_xrange.py
spec_plots/utils/specutils/set_plot_yrange.py
spec_plots/utils/specutils/specutilserror.py
spec_plots/utils/specutils/stitch_components.py
spec_plots/utils/specutils/test_placeholder.py
spec_plots/utils/specutils_cos/__init__.py
spec_plots/utils/specutils_cos/check_segments.py
spec_plots/utils/specutils_cos/cosspectrum.py
spec_plots/utils/specutils_cos/extract_subspec.py
spec_plots/utils/specutils_cos/get_segment_names.py
spec_plots/utils/specutils_cos/make_fits.py
spec_plots/utils/specutils_cos/plotspec.py
spec_plots/utils/specutils_cos/readspec.py
spec_plots/utils/specutils_hasp/__init__.py
spec_plots/utils/specutils_hasp/haspspectrum.py
spec_plots/utils/specutils_hasp/plotspec.py
spec_plots/utils/specutils_hasp/readspec.py
spec_plots/utils/specutils_jwst/__init__.py
spec_plots/utils/specutils_jwst/jwstspectrum.py
spec_plots/utils/specutils_jwst/plotspec.py
spec_plots/utils/specutils_jwst/readspec.py
spec_plots/utils/specutils_miri/__init__.py
spec_plots/utils/specutils_miri/mirispectrum.py
spec_plots/utils/specutils_miri/plotspec.py
spec_plots/utils/specutils_miri/readspec.py
spec_plots/utils/specutils_stis/__init__.py
spec_plots/utils/specutils_stis/get_association_indices.py
spec_plots/utils/specutils_stis/plotspec.py
spec_plots/utils/specutils_stis/readspec.py
spec_plots-1.37.1.dist-info/LICENSE.rst
spec_plots-1.37.1.dist-info/METADATA
spec_plots-1.37.1.dist-info/WHEEL
spec_plots-1.37.1.dist-info/entry_points.txt
spec_plots-1.37.1.dist-info/top_level.txt
spec_plots-1.37.1.dist-info/RECORD
